octo_pipeline_python/backends/file/__init__.py
octo_pipeline_python/backends/file/file_backend.py
octo_pipeline_python/backends/file/actions/__init__.py
octo_pipeline_python/backends/file/actions/file_download.py
octo_pipeline_python/backends/file/models/__init__.py
octo_pipeline_python/backends/file/models/file_model.py
octo_pipeline_backend_file_python-1.3.2.dist-info/LICENSE.txt
octo_pipeline_backend_file_python-1.3.2.dist-info/METADATA
octo_pipeline_backend_file_python-1.3.2.dist-info/README.md
octo_pipeline_backend_file_python-1.3.2.dist-info/WHEEL
octo_pipeline_backend_file_python-1.3.2.dist-info/top_level.txt
octo_pipeline_backend_file_python-1.3.2.dist-info/RECORD
